mmpdenet/__init__.py
mmpdenet-0.1.0.dist-info/METADATA
mmpdenet-0.1.0.dist-info/WHEEL
mmpdenet-0.1.0.dist-info/RECORD
