Metadata-Version: 2.1
Name: mmpdenet
Version: 0.1.0
Summary: 
Author: Shao-Ting Chiu
Author-email: stchiu@email.tamu.edu
Requires-Python: >=3.10,<4.0
Classifier: Programming Language :: Python :: 3
Classifier: Programming Language :: Python :: 3.10
Classifier: Programming Language :: Python :: 3.11
Classifier: Programming Language :: Python :: 3.12
Requires-Dist: equinox (>=0.11.4,<0.12.0)
Requires-Dist: jax (>=0.4.27,<0.5.0)
Requires-Dist: numpy (>=1.26.4,<2.0.0)
Requires-Dist: optax (>=0.2.2,<0.3.0)
